octoprint_pi_support/__init__.py
octoprint_pi_support/static/clientjs/pi_support.js
octoprint_pi_support/static/css/pi_support.css
octoprint_pi_support/static/js/pi_support.js
octoprint_pi_support/templates/pi_support_about_octopi.jinja2
octoprint_pi_support/templates/pi_support_about_octopiuptodate.jinja2
octoprint_pi_support/templates/pi_support_navbar.jinja2
octoprint_pi_support/templates/pi_support_settings.jinja2
octoprint_pi_support/translations/de/LC_MESSAGES/messages.mo
octoprint_pi_support/translations/de/LC_MESSAGES/messages.po
OctoPrint_PiSupport-2023.10.10.dist-info/LICENSE
OctoPrint_PiSupport-2023.10.10.dist-info/METADATA
OctoPrint_PiSupport-2023.10.10.dist-info/WHEEL
OctoPrint_PiSupport-2023.10.10.dist-info/entry_points.txt
OctoPrint_PiSupport-2023.10.10.dist-info/top_level.txt
OctoPrint_PiSupport-2023.10.10.dist-info/RECORD
