Metadata-Version: 2.1
Name: OctoPrint-PiSupport
Version: 2023.10.10
Summary: Provides additional information about your Pi in the UI
Home-page: https://github.com/OctoPrint/OctoPrint-PiSupport
Author: Gina Häußge
Author-email: gina@octoprint.org
License: AGPLv3
Platform: UNKNOWN
Provides-Extra: develop
